aws_recommendation_a19/__init__.py
aws_recommendation_a19/cloudwatch.py
aws_recommendation_a19/cost_estimations.py
aws_recommendation_a19/dynamodb.py
aws_recommendation_a19/ebs.py
aws_recommendation_a19/ec2.py
aws_recommendation_a19/elb.py
aws_recommendation_a19/kms.py
aws_recommendation_a19/rds.py
aws_recommendation_a19/recommendation.py
aws_recommendation_a19/redshift.py
aws_recommendation_a19/s3.py
aws_recommendation_a19/truted_advisor.py
aws_recommendation_a19/utils.py
aws_recommendation_a19-0.1.11.dist-info/LICENCE
aws_recommendation_a19-0.1.11.dist-info/METADATA
aws_recommendation_a19-0.1.11.dist-info/WHEEL
aws_recommendation_a19-0.1.11.dist-info/top_level.txt
aws_recommendation_a19-0.1.11.dist-info/RECORD
